TurbineEvaluateDiagnosisPackage/__init__.py
TurbineEvaluateDiagnosisPackage/toolbox/__init__.py
TurbineEvaluateDiagnosisPackage/toolbox/v1/Method_GuideVaneServomotor.py
TurbineEvaluateDiagnosisPackage/toolbox/v1/Method_MainShaftSealing.py
TurbineEvaluateDiagnosisPackage/toolbox/v1/Method_TailTube.py
TurbineEvaluateDiagnosisPackage/toolbox/v1/Method_Turbine.py
TurbineEvaluateDiagnosisPackage/toolbox/v1/Method_WaterDistributor.py
TurbineEvaluateDiagnosisPackage/toolbox/v1/Method_WaterGuideBearing.py
TurbineEvaluateDiagnosisPackage/toolbox/v1/__init__.py
TurbineEvaluateDiagnosisPackage/validation/__init__.py
TurbineEvaluateDiagnosisPackage/validation/v1/Validation_GuideVaneServomotor.py
TurbineEvaluateDiagnosisPackage/validation/v1/Validation_MainShaftSealing_ConditionJudgement.py
TurbineEvaluateDiagnosisPackage/validation/v1/Validation_MainShaftSealing_LubricateWaterMembrane.py
TurbineEvaluateDiagnosisPackage/validation/v1/Validation_MainShaftSealing_ShaftSealingLeakage.py
TurbineEvaluateDiagnosisPackage/validation/v1/Validation_MainShaftSealing_ShaftSealingWearing.py
TurbineEvaluateDiagnosisPackage/validation/v1/Validation_TailTube.py
TurbineEvaluateDiagnosisPackage/validation/v1/Validation_Turbine.py
TurbineEvaluateDiagnosisPackage/validation/v1/Validation_WaterDistributor.py
TurbineEvaluateDiagnosisPackage/validation/v1/Validation_WaterGuideBearing.py
TurbineEvaluateDiagnosisPackage/validation/v1/__init__.py
TurbineEvaluateDiagnosisPackage-1.0.0.dist-info/LICENSE
TurbineEvaluateDiagnosisPackage-1.0.0.dist-info/METADATA
TurbineEvaluateDiagnosisPackage-1.0.0.dist-info/WHEEL
TurbineEvaluateDiagnosisPackage-1.0.0.dist-info/top_level.txt
TurbineEvaluateDiagnosisPackage-1.0.0.dist-info/RECORD
