Metadata-Version: 2.1
Name: TurbineEvaluateDiagnosisPackage
Version: 1.0.0
Summary: 1.Method_MainShaftSealing: 主轴密封健康评估与故障诊断模块所需特征参数计算;2.Method_GuideVaneServomotor: 导叶接力器健康评估与故障诊断模块所需特征参数计算;3.Method_WaterGuideBearing: 水导轴承健康评估与故障诊断模块所需特征参数计算;4.Method_Turbine:转轮健康评估与故障诊断模块所需特征参数计算;5.Method_TailTube: 尾水管健康评估与故障诊断模块所需特征参数计算;6.Method_WaterDistributor: 导水机构健康评估与故障诊断模块所需特征参数计算
Home-page: https://github.com/zhaozl1123
Author: zhaozl1123
Author-email: 545362989@qq.com
License: MIT
Platform: UNKNOWN
Classifier: License :: OSI Approved :: MIT License
Classifier: Programming Language :: Python
Classifier: Programming Language :: Python :: 3
Classifier: Programming Language :: Python :: 3.6
Classifier: Programming Language :: Python :: Implementation :: CPython
Classifier: Programming Language :: Python :: Implementation :: PyPy
Requires-Python: >=3.7.0
License-File: LICENSE
Requires-Dist: numpy (==1.18.5)
Requires-Dist: scipy (==1.4.1)
Requires-Dist: pandas (==1.1.0)
